{
  "name": "Cariyāpiṭakapāḷi",
  "title": {
    "pali": "Cariyāpiṭakapāḷi",
    "english": "",
    "sinhala": ""
  },
  "footer": {
    "pali": "Cariyāpiṭakaṃ niṭṭhitaṃ.",
    "english": "",
    "sinhala": ""
  },
  "chapters": [
    {
      "id": "cp.1",
      "title": {
        "pali": "Akittivaggo",
        "english": "",
        "sinhala": ""
      }
    },
    {
      "id": "cp.2",
      "title": {
        "pali": "Hatthināgavaggo",
        "english": "",
        "sinhala": ""
      }
    },
    {
      "id": "cp.3",
      "title": {
        "pali": "Yudhañjayavaggo",
        "english": "",
        "sinhala": ""
      }
    }
  ]
}