{
  "id": "pv.41",
  "title": {
    "pali": "Serīsakapetavatthu",
    "english": "",
    "sinhala": ""
  },
  "sections": [
    {
      "number": 604,
      "pali": "[vi. va. 1228] Suṇotha yakkhassa vāṇijāna ca, samāgamo yattha tadā ahosi; Yathā kathaṃ itaritarena cāpi, subhāsitaṃ tañca suṇātha sabbe.",
      "english": "",
      "sinhala": "",
      "paliTitle": ""
    },
    {
      "number": 605,
      "pali": "Yo so ahu rājā pāyāsi nāma [nāmo (sī.)], bhummānaṃ sahabyagato yasassī; So modamānova sake vimāne, amānuso mānuse ajjhabhāsīti.",
      "english": "",
      "sinhala": "",
      "paliTitle": ""
    },
    {
      "number": 606,
      "pali": "‘‘Vaṅke araññe amanussaṭṭhāne, kantāre appodake appabhakkhe; Suduggame vaṇṇupathassa majjhe, vaṅkaṃbhayā naṭṭhamanā manussā.",
      "english": "",
      "sinhala": "",
      "paliTitle": ""
    },
    {
      "number": 607,
      "pali": "‘‘Nayidha phalā mūlamayā ca santi, upādānaṃ natthi kutodha bhakkho [bhikkho (ka.)]; Aññatra paṃsūhi ca vālukāhi ca, tatāhi uṇhāhi ca dāruṇāhi ca.",
      "english": "",
      "sinhala": "",
      "paliTitle": ""
    },
    {
      "number": 608,
      "pali": "‘‘Ujjaṅgalaṃ tattamivaṃ kapālaṃ, anāyasaṃ paralokena tulyaṃ; Luddānamāvāsamidaṃ purāṇaṃ, bhūmippadeso abhisattarūpo.",
      "english": "",
      "sinhala": "",
      "paliTitle": ""
    },
    {
      "number": 609,
      "pali": "‘‘‘Atha tumhe kena vaṇṇena, kimāsamānā imaṃ padesaṃ hi; Anupaviṭṭhā sahasā samacca, lobhā bhayā atha vā sampamūḷhā’’’ti.",
      "english": "",
      "sinhala": "",
      "paliTitle": ""
    },
    {
      "number": 610,
      "pali": "‘‘Magadhesu aṅgesu ca satthavāhā, āropayitvā paṇiyaṃ puthuttaṃ; Te yāmase sindhusovīrabhūmiṃ, dhanatthikā uddayaṃ patthayānā.",
      "english": "",
      "sinhala": "",
      "paliTitle": ""
    },
    {
      "number": 611,
      "pali": "‘‘Divā pipāsaṃ nadhivāsayantā, yoggānukampañca samekkhamānā; Etena vegena āyāma sabbe, rattiṃ maggaṃ paṭipannā vikāle.",
      "english": "",
      "sinhala": "",
      "paliTitle": ""
    },
    {
      "number": 612,
      "pali": "‘‘Te duppayātā aparaddhamaggā, andhākulā vippanaṭṭhā araññe; Suduggame vaṇṇupathassa majjhe, disaṃ na jānāma pamūḷhacittā.",
      "english": "",
      "sinhala": "",
      "paliTitle": ""
    },
    {
      "number": 613,
      "pali": "‘‘Idañca disvāna adiṭṭhapubbaṃ, vimānaseṭṭhañca tavañca yakkha; Tatuttariṃ jīvitamāsamānā, disvā patītā sumanā udaggā’’ti.",
      "english": "",
      "sinhala": "",
      "paliTitle": ""
    },
    {
      "number": 614,
      "pali": "‘‘Pāraṃ samuddassa imañca vaṇṇuṃ, vettācaraṃ [vettaṃ paraṃ (syā.), vettācāraṃ (ka.)] saṅkupathañca maggaṃ; Nadiyo pana pabbatānañca duggā, puthuddisā gacchatha bhogahetu.",
      "english": "",
      "sinhala": "",
      "paliTitle": ""
    },
    {
      "number": 615,
      "pali": "‘‘Pakkhandiyāna vijitaṃ paresaṃ, verajjake mānuse pekkhamānā; Yaṃ vo sutaṃ vā atha vāpi diṭṭhaṃ, accherakaṃ taṃ vo suṇoma tātā’’ti.",
      "english": "",
      "sinhala": "",
      "paliTitle": ""
    },
    {
      "number": 616,
      "pali": "‘‘Itopi accherataraṃ kumāra, na no sutaṃ vā atha vāpi diṭṭhaṃ; Atītamānussakameva sabbaṃ, disvā na tappāma anomavaṇṇaṃ.",
      "english": "",
      "sinhala": "",
      "paliTitle": ""
    },
    {
      "number": 617,
      "pali": "‘‘Vehāyasaṃ pokkharañño savanti, pahūtamalyā [pahūtamālyā (syā.)] bahupuṇḍarīkā; Dumā cime niccaphalūpapannā, atīva gandhā surabhiṃ pavāyanti.",
      "english": "",
      "sinhala": "",
      "paliTitle": ""
    },
    {
      "number": 618,
      "pali": "‘‘Veḷūriyathambhā satamussitāse, silāpavāḷassa ca āyataṃsā; Masāragallā sahalohitaṅgā, thambhā ime jotirasāmayāse.",
      "english": "",
      "sinhala": "",
      "paliTitle": ""
    },
    {
      "number": 619,
      "pali": "‘‘Sahassathambhaṃ atulānubhāvaṃ, tesūpari sādhumidaṃ vimānaṃ; Ratanantaraṃ kañcanavedimissaṃ, tapanīyapaṭṭehi ca sādhuchannaṃ.",
      "english": "",
      "sinhala": "",
      "paliTitle": ""
    },
    {
      "number": 620,
      "pali": "‘‘Jambonaduttattamidaṃ sumaṭṭho, pāsādasopāṇaphalūpapanno; Daḷho ca vaggu ca susaṅgato ca [vaggu sumukho susaṅgato (sī.)], atīva nijjhānakhamo manuñño.",
      "english": "",
      "sinhala": "",
      "paliTitle": ""
    },
    {
      "number": 621,
      "pali": "‘‘Ratanantarasmiṃ bahuannapānaṃ, parivārito accharāsaṅgaṇena; Murajaālambaratūriyaghuṭṭho, abhivanditosi thutivandanāya.",
      "english": "",
      "sinhala": "",
      "paliTitle": ""
    },
    {
      "number": 622,
      "pali": "‘‘So modasi nārigaṇappabodhano, vimānapāsādavare manorame; Acintiyo sabbaguṇūpapanno, rājā yathā vessavaṇo naḷinyā [naḷiññaṃ (ka.)].",
      "english": "",
      "sinhala": "",
      "paliTitle": ""
    },
    {
      "number": 623,
      "pali": "‘‘Devo nu āsi udavāsi yakkho, udāhu devindo manussabhūto; Pucchanti taṃ vāṇijā satthavāhā, ācikkha ko nāma tuvaṃsi yakkho’’ti.",
      "english": "",
      "sinhala": "",
      "paliTitle": ""
    },
    {
      "number": 624,
      "pali": "‘‘Serīsako nāma ahamhi yakkho, kantāriyo vaṇṇupathamhi gutto; Imaṃ padesaṃ abhipālayāmi, vacanakaro vessavaṇassa rañño’’ti.",
      "english": "",
      "sinhala": "",
      "paliTitle": ""
    },
    {
      "number": 625,
      "pali": "‘‘Adhiccaladdhaṃ pariṇāmajaṃ te, sayaṃ kataṃ udāhu devehi dinnaṃ; Pucchanti taṃ vāṇijā satthavāhā, kathaṃ tayā laddhamidaṃ manuñña’’nti.",
      "english": "",
      "sinhala": "",
      "paliTitle": ""
    },
    {
      "number": 626,
      "pali": "‘‘Nādhiccaladdhaṃ na pariṇāmajaṃ me, na sayaṃ kataṃ na hi devehi dinnaṃ; Sakehi kammehi apāpakehi, puññehi me laddhamidaṃ manuñña’’nti.",
      "english": "",
      "sinhala": "",
      "paliTitle": ""
    },
    {
      "number": 627,
      "pali": "‘‘Kiṃ te vataṃ kiṃ pana brahmacariyaṃ, kissa suciṇṇassa ayaṃ vipāko; Pucchanti taṃ vāṇijā satthavāhā, kathaṃ tayā laddhamidaṃ vimāna’’nti.",
      "english": "",
      "sinhala": "",
      "paliTitle": ""
    },
    {
      "number": 628,
      "pali": "‘‘Mamaṃ pāyāsīti ahu samaññā, rajjaṃ yadā kārayiṃ kosalānaṃ; Natthikadiṭṭhi kadariyo pāpadhammo, ucchedavādī ca tadā ahosiṃ.",
      "english": "",
      "sinhala": "",
      "paliTitle": ""
    },
    {
      "number": 629,
      "pali": "‘‘Samaṇo ca kho āsi kumārakassapo, bahussuto cittakathī uḷāro; So me tadā dhammakathaṃ abhāsi, diṭṭhivisūkāni vinodayī me.",
      "english": "",
      "sinhala": "",
      "paliTitle": ""
    },
    {
      "number": 630,
      "pali": "‘‘Tāhaṃ tassa dhammakathaṃ suṇitvā, upāsakattaṃ paṭidevayissaṃ; Pāṇātipātā virato ahosiṃ, loke adinnaṃ parivajjayissaṃ; Amajjapo no ca musā abhāṇiṃ, sakena dārena ca ahosi tuṭṭho.",
      "english": "",
      "sinhala": "",
      "paliTitle": ""
    },
    {
      "number": 631,
      "pali": "‘‘Taṃ me vataṃ taṃ pana brahmacariyaṃ, tassa suciṇṇassa ayaṃ vipāko; Teheva kammehi apāpakehi, puññehi me laddhamidaṃ vimāna’’nti.",
      "english": "",
      "sinhala": "",
      "paliTitle": ""
    },
    {
      "number": 632,
      "pali": "‘‘Saccaṃ kirāhaṃsu narā sapaññā, anaññathā vacanaṃ paṇḍitānaṃ; Yahiṃ yahiṃ gacchati puññakammo, tahiṃ tahiṃ modati kāmakāmī.",
      "english": "",
      "sinhala": "",
      "paliTitle": ""
    },
    {
      "number": 633,
      "pali": "‘‘Yahiṃ yahiṃ sokapariddavo ca, vadho ca bandho ca parikkileso; Tahiṃ tahiṃ gacchati pāpakammo, na muccati duggatiyā kadācī’’ti.",
      "english": "",
      "sinhala": "",
      "paliTitle": ""
    },
    {
      "number": 634,
      "pali": "‘‘Sammūḷharūpova jano ahosi, asmiṃ muhutte kalalīkatova; Janassimassa tuyhañca kumāra, appaccayo kena nu kho ahosī’’ti.",
      "english": "",
      "sinhala": "",
      "paliTitle": ""
    },
    {
      "number": 635,
      "pali": "‘‘Ime ca sirīsavanā [ime sirīsūpavanā ca (sī.), imepi sirīsavanā ca (pī. ka.)] tātā, dibbā gandhā surabhī sampavanti; Te sampavāyanti imaṃ vimānaṃ, divā ca ratto ca tamaṃ nihantvā.",
      "english": "",
      "sinhala": "",
      "paliTitle": ""
    },
    {
      "number": 636,
      "pali": "‘‘Imesañca kho vassasataccayena, sipāṭikā phalati ekamekā; Mānussakaṃ vassasataṃ atītaṃ, yadagge kāyamhi idhūpapanno.",
      "english": "",
      "sinhala": "",
      "paliTitle": ""
    },
    {
      "number": 637,
      "pali": "‘‘Disvānahaṃ vassasatāni pañca, asmiṃ vimāne ṭhatvāna tātā; Āyukkhayā puññakkhayā cavissaṃ, teneva sokena pamucchitosmī’’ti.",
      "english": "",
      "sinhala": "",
      "paliTitle": ""
    },
    {
      "number": 638,
      "pali": "‘‘Kathaṃ nu soceyya tathāvidho so, laddhā vimānaṃ atulaṃ cirāya; Ye cāpi kho ittaramupapannā, te nūna soceyyuṃ parittapuññā’’ti.",
      "english": "",
      "sinhala": "",
      "paliTitle": ""
    },
    {
      "number": 639,
      "pali": "‘‘Anucchaviṃ ovadiyañca me taṃ, yaṃ maṃ tumhe peyyavācaṃ vadetha; Tumhe ca kho tātā mayānuguttā, yenicchakaṃ tena paletha sotthi’’nti.",
      "english": "",
      "sinhala": "",
      "paliTitle": ""
    },
    {
      "number": 640,
      "pali": "‘‘Gantvā mayaṃ sindhusovīrabhūmiṃ, dhannatthikā uddayaṃ patthayānā; Yathāpayogā paripuṇṇacāgā, kāhāma serīsamahaṃ uḷāra’’nti.",
      "english": "",
      "sinhala": "",
      "paliTitle": ""
    },
    {
      "number": 641,
      "pali": "‘‘Mā ceva serīsamahaṃ akattha, sabbañca vo bhavissati yaṃ vadetha; Pāpāni kammāni vivajjayātha, dhammānuyogañca adhiṭṭhahātha.",
      "english": "",
      "sinhala": "",
      "paliTitle": ""
    },
    {
      "number": 642,
      "pali": "‘‘Upāsako atthi imamhi saṅghe, bahussuto sīlavatūpapanno; Saddho ca cāgī ca supesalo ca, vicakkhaṇo santusito mutīmā.",
      "english": "",
      "sinhala": "",
      "paliTitle": ""
    },
    {
      "number": 643,
      "pali": "‘‘Sañjānamāno na musā bhaṇeyya, parūpaghātāya ca cetayeyya; Vebhūtikaṃ pesuṇaṃ no kareyya, saṇhañca vācaṃ sakhilaṃ bhaṇeyya.",
      "english": "",
      "sinhala": "",
      "paliTitle": ""
    },
    {
      "number": 644,
      "pali": "‘‘Sagāravo sappaṭisso vinīto, apāpako adhisīle visuddho; So mātaraṃ pitarañcāpi jantu, dhammena poseti ariyavutti.",
      "english": "",
      "sinhala": "",
      "paliTitle": ""
    },
    {
      "number": 645,
      "pali": "‘‘Maññe so mātāpitūnaṃ kāraṇā, bhogāni pariyesati na attahetu; Mātāpitūnañca yo accayena, nekkhammapoṇo carissati brahmacariyaṃ.",
      "english": "",
      "sinhala": "",
      "paliTitle": ""
    },
    {
      "number": 646,
      "pali": "‘‘Ujū avaṅko asaṭho amāyo, na lesakappena ca vohareyya; So tādiso sukatakammakārī, dhamme ṭhito kinti labhetha dukkhaṃ.",
      "english": "",
      "sinhala": "",
      "paliTitle": ""
    },
    {
      "number": 647,
      "pali": "‘‘Taṃ kāraṇā pātukatomhi attanā, tasmā dhammaṃ passatha vāṇijāse; Aññatra teniha bhasmī [bhasmi (syā.), bhasma (ka.)] bhavetha, andhākulā vippanaṭṭhā araññe; Taṃ khippamānena lahuṃ parena, sukho have sappurisena saṅgamo’’ti.",
      "english": "",
      "sinhala": "",
      "paliTitle": ""
    },
    {
      "number": 648,
      "pali": "‘‘Kiṃ nāma so kiñca karoti kammaṃ, kiṃ nāmadheyyaṃ kiṃ pana tassa gottaṃ; Mayampi naṃ daṭṭhukāmamha yakkha, yassānukampāya idhāgatosi; Lābhā hi tassa yassa tuvaṃ pihesī’’ti.",
      "english": "",
      "sinhala": "",
      "paliTitle": ""
    },
    {
      "number": 649,
      "pali": "‘‘Yo kappako sambhavanāmadheyyo, upāsako kocchaphalūpajīvī; Jānātha naṃ tumhākaṃ pesiyo so, mā kho naṃ hīḷittha supesalo so’’ti.",
      "english": "",
      "sinhala": "",
      "paliTitle": ""
    },
    {
      "number": 650,
      "pali": "‘‘Jānāmase yaṃ tvaṃ pavadesi yakkha, na kho naṃ jānāma sa edisoti; Mayampi naṃ pūjayissāma yakkha, sutvāna tuyhaṃ vacanaṃ uḷāra’’nti.",
      "english": "",
      "sinhala": "",
      "paliTitle": ""
    },
    {
      "number": 651,
      "pali": "‘‘Ye keci imasmiṃ satthe manussā, daharā mahantā athavāpi majjhimā; Sabbeva te ālambantu vimānaṃ, passantu puññānaṃ phalaṃ kadariyā’’ti.",
      "english": "",
      "sinhala": "",
      "paliTitle": ""
    },
    {
      "number": 652,
      "pali": "Te tattha sabbeva ‘ahaṃ pure’ti, taṃ kappakaṃ tattha purakkhatvā [purakkhipitvā (sī.)]; Sabbeva te ālambiṃsu vimānaṃ, masakkasāraṃ viya vāsavassa.",
      "english": "",
      "sinhala": "",
      "paliTitle": ""
    },
    {
      "number": 653,
      "pali": "Te tattha sabbeva ‘ahaṃ pure’ti, upāsakattaṃ paṭivedayiṃsu; Pāṇātipātā paṭiviratā ahesuṃ, loke adinnaṃ parivajjayiṃsu; Amajjapā no ca musā bhaṇiṃsu, sakena dārena ca ahesuṃ tuṭṭhā.",
      "english": "",
      "sinhala": "",
      "paliTitle": ""
    },
    {
      "number": 654,
      "pali": "Te tattha sabbeva ‘ahaṃ pure’ti, upāsakattaṃ paṭivedayitvā; Pakkāmi sattho anumodamāno, yakkhiddhiyā anumato punappunaṃ.",
      "english": "",
      "sinhala": "",
      "paliTitle": ""
    },
    {
      "number": 655,
      "pali": "Gantvāna te sindhusovīrabhūmiṃ, dhanatthikā uddayaṃ [udaya (pī. ka.)] patthayānā; Yathāpayogā paripuṇṇalābhā, paccāgamuṃ pāṭaliputtamakkhataṃ.",
      "english": "",
      "sinhala": "",
      "paliTitle": ""
    },
    {
      "number": 656,
      "pali": "Gantvāna te saṅgharaṃ sotthivanto, puttehi dārehi samaṅgibhūtā; Ānandī vittā sumanā patītā, akaṃsu serīsamahaṃ uḷāraṃ; Serīsakaṃ te pariveṇaṃ māpayiṃsu.",
      "english": "",
      "sinhala": "",
      "paliTitle": ""
    },
    {
      "number": 657,
      "pali": "Etādisā sappurisāna sevanā, mahatthikā dhammaguṇāna sevanā; Ekassa atthāya upāsakassa, sabbeva sattā sukhitā [sukhino (pī. ka.)] ahesunti. Serīsakapetavatthu dutiyaṃ. Bhāṇavāraṃ tatiyaṃ niṭṭhitaṃ.",
      "english": "",
      "sinhala": "",
      "paliTitle": ""
    }
  ],
  "footer": {
    "pali": "",
    "english": "",
    "sinhala": ""
  }
}